odoo/addons/partner_noncommercial/README.rst
odoo/addons/partner_noncommercial/__init__.py
odoo/addons/partner_noncommercial/__manifest__.py
odoo/addons/partner_noncommercial/i18n/nl.po
odoo/addons/partner_noncommercial/i18n/partner_noncommercial.pot
odoo/addons/partner_noncommercial/i18n/sl.po
odoo/addons/partner_noncommercial/i18n_extra/en.po
odoo/addons/partner_noncommercial/i18n_extra/nl.po
odoo/addons/partner_noncommercial/readme/CONFIGURE.rst
odoo/addons/partner_noncommercial/readme/CONTRIBUTORS.rst
odoo/addons/partner_noncommercial/readme/DESCRIPTION.rst
odoo/addons/partner_noncommercial/readme/USAGE.rst
odoo/addons/partner_noncommercial/static/description/icon.png
odoo/addons/partner_noncommercial/static/description/index.html
odoo/addons/partner_noncommercial/views/menu.xml
odoo/addons/partner_noncommercial/views/res_partner.xml
odoo11_addon_partner_noncommercial-11.0.1.0.0.99.dev8.dist-info/METADATA
odoo11_addon_partner_noncommercial-11.0.1.0.0.99.dev8.dist-info/WHEEL
odoo11_addon_partner_noncommercial-11.0.1.0.0.99.dev8.dist-info/top_level.txt
odoo11_addon_partner_noncommercial-11.0.1.0.0.99.dev8.dist-info/RECORD
